odoo-manager/__init__.py
odoo_manager/__init__.py
odoo_manager/__main__.py
odoo_manager/cli/__init__.py
odoo_manager/cli/cli.py
odoo_manager/cli/commands/__init__.py
odoo_manager/cli/commands/base.py
odoo_manager/cli/commands/hello.py
odoo_manager/cli/commands/setup.py
odoo_manager/cli/exceptions/__init__.py
odoo_manager/cli/exceptions/command_exception.py
odoo_manager/core/__init__.py
odoo_manager/core/configs.py
odoo_manager/core/database.py
odoo_manager/core/gcloud.py
odoo_manager/core/git.py
odoo_manager/core/helpers.py
odoo_manager/core/misc.py
odoo_manager/core/paths.py
odoo_manager/core/shell.py
odoo_manager/core/tasks.py
odoo_manager/core/validation.py
odoo_manager-0.0.2.dist-info/DESCRIPTION.rst
odoo_manager-0.0.2.dist-info/METADATA
odoo_manager-0.0.2.dist-info/RECORD
odoo_manager-0.0.2.dist-info/WHEEL
odoo_manager-0.0.2.dist-info/entry_points.txt
odoo_manager-0.0.2.dist-info/metadata.json
odoo_manager-0.0.2.dist-info/top_level.txt
tasks/__init__.py
tasks/curl.py
tasks/db.py
tasks/formatter.py
tasks/general.py
tasks/make.py
tasks/run.py
tasks/scaffold.py
tasks/setups.py
tasks/test.py
tasks/wiki.py
tasks/lib/__init__.py
tasks/lib/configs.py
tasks/lib/database.py
tasks/lib/gcloud.py
tasks/lib/helpers.py
tasks/lib/paths.py
tasks/lib/shell.py
tasks/lib/tasks.py
tasks/lib/validation.py
