Metadata-Version: 2.0
Name: odoo-manager
Version: 0.0.2
Summary: Odoo manager utility
Home-page: UNKNOWN
Author: Blue Stingray
Author-email: odoo@bluestingray.com
License: UNKNOWN
Platform: UNKNOWN
Classifier: Programming Language :: Python :: 3
Classifier: License :: OSI Approved :: GNU Lesser General Public License v3 or later (LGPLv3+)
Classifier: Operating System :: OS Independent
Requires-Python: >=3.3
Provides-Extra: test
Requires-Dist: docopt
Requires-Dist: invoke (==1.1.*)
Requires-Dist: configparser (==3.7.3)
Provides-Extra: test
Requires-Dist: coverage; extra == 'test'
Requires-Dist: pytest; extra == 'test'
Requires-Dist: pytest-cov; extra == 'test'
